setop/__init__.py
setOp-0.1.1.dist-info/LICENSE
setOp-0.1.1.dist-info/METADATA
setOp-0.1.1.dist-info/WHEEL
setOp-0.1.1.dist-info/entry_points.txt
setOp-0.1.1.dist-info/top_level.txt
setOp-0.1.1.dist-info/RECORD
