Metadata-Version: 2.1
Name: setOp
Version: 0.1.1
Summary: Compared files with through python set operations.
Home-page: https://github.com/onewesong/setOp
Author: wws
Author-email: onewesong@gmail.com
License: UNKNOWN
Platform: UNKNOWN
